physical_quantities_coordinates/__init__.py
physical_quantities_coordinates-0.5.1.dist-info/METADATA
physical_quantities_coordinates-0.5.1.dist-info/WHEEL
physical_quantities_coordinates-0.5.1.dist-info/top_level.txt
physical_quantities_coordinates-0.5.1.dist-info/RECORD
