Metadata-Version: 2.1
Name: physical-quantities-coordinates
Version: 0.5.1
Summary: A collection of classes for representing the physical measurable quantities and the methods to locate them
Home-page: https://gitlab.com/frankmobley/physical_quantities_coordinates
Author: Dr. Frank Mobley
Author-email: frank.mobley.1@afrl.af.mil
